[
    {
        "_id": "29",
        "name": "Ajaib",
        "type": "Mutual Funds",
        "category": ["Coming Soon", "Crypto & Stock"],
        "imageUrl": [{
                "icon": "https://data-polahub.herokuapp.com/images/ajaib.png"
            },
            {
                "card": "https://data-polahub.herokuapp.com/images/card/ajaib-lock.png"
            },
            {
                "pattern": []
            }
        ],
        "isCategory": true,
        "provider": "",
        "copyright": "",
        "appstore": "",
        "playstore": "",
        "country": "Indonesia",
        "lock": true,
        "new": false,
        "color": "#ebecef"
    },

    {
        "_id": "30",
        "name": "GoPayLater",
        "type": "Lending",
        "category": ["Coming Soon", "Finance", "Gojek Product"],
        "imageUrl": [{
                "icon": "https://data-polahub.herokuapp.com/images/gojek.png"
            },
            {
                "card": "https://data-polahub.herokuapp.com/images/card/gopaylater-lock.png"
            },
            {
                "pattern": []
            }
        ],
        "isCategory": true,
        "provider": "PT Go-jek Indonesia",
        "copyright": "© PT Aplikasi Karya Anak Bangsa",
        "appstore": "https://apps.apple.com/id/app/gojek/id944875099",
        "playstore": "https://play.google.com/store/apps/details?id=com.gojek.app&hl=in&gl=US",
        "country": "Indonesia",
        "lock": true,
        "new": false,
        "color": "#ebecef"
    }, {
        "_id": "36",
        "name": "TurboVPN",
        "type": "VPN",
        "category": ["Coming Soon", "Productivity"],
        "imageUrl": [{
                "icon": "https://data-polahub.herokuapp.com/images/turbo.png"
            },
            {
                "card": "https://data-polahub.herokuapp.com/images/card/turbo-lock.png"
            },
            {
                "pattern": []
            }
        ],
        "isCategory": true,
        "provider": "",
        "copyright": "",
        "appstore": "",
        "playstore": "",
        "country": "",
        "lock": true,
        "new": false,
        "color": "#ebecef"
    },
    {
        "_id": "37",
        "name": "ZOOM",
        "type": "Video Conference",
        "category": ["Coming Soon", "Business"],
        "imageUrl": [{
                "icon": "https://data-polahub.herokuapp.com/images/zoom.png"
            },
            {
                "card": "https://data-polahub.herokuapp.com/images/card/zoom-lock.png"
            },
            {
                "pattern": []
            }
        ],
        "isCategory": true,
        "provider": "",
        "copyright": "",
        "appstore": "",
        "playstore": "",
        "country": "",
        "lock": true,
        "new": false,
        "color": "#ebecef"
    },
    {
        "_id": "79",
        "name": "Octopus",
        "type": "Waste Management",
        "category": [ "Lifestyle"],
        "imageUrl": [{
            "icon": "https://ndbqcbbgigoygotysyae.supabase.co/storage/v1/object/public/app/Vidio/logo.webp"
          },
          {
            "card": "https://ndbqcbbgigoygotysyae.supabase.co/storage/v1/object/public/app/Vidio/mockup.webp"
          },
          {
            "pattern": [
             
            ]
          }
        ],
        "isCategory": true,
        "provider": "Octopus Waste Management PTE. LTD.",
        "copyright": "© Octopus Waste Management PTE. LTD.",
        "appstore": "https://apps.apple.com/us/app/octopus-sampah-jadi-berharga/id1515879876",
        "playstore": "https://play.google.com/store/apps/details?id=com.octopus.customer&hl=id&gl=US",
        "country": "Indonesia",
        "lock": true,
        "new": false,
        "new_color": "#D2EFFB",
        "color": "rgba(0, 179, 249, 0.16)"
      },
      {
        "_id": "161",
        "name": "Baemin",
        "type": "F&B Delivery",
        "category": [ "Food & Drink"],
        "imageUrl": [{
            "icon": "https://ndbqcbbgigoygotysyae.supabase.co/storage/v1/object/public/app/Vidio/logo.webp"
          },
          {
            "card": "https://ndbqcbbgigoygotysyae.supabase.co/storage/v1/object/public/app/Vidio/mockup.webp"
          },
          {
            "pattern": [
             
            ]
          }
        ],
        "isCategory": true,
        "provider": "WOOWA BROTHERS VIETNAM COMPANY LIMITED.",
        "copyright": "© 2022 Woowa Brothers Asia Holdings Pte. Ltd.",
        "appstore": "https://apps.apple.com/vn/app/baemin-food-delivery-app/id1458845623",
        "playstore": "https://play.google.com/store/apps/details?id=com.woowahan.vn.baemin&hl=en_SG&gl=US",
        "country": "Vietnam",
        "lock": false,
        "new": true,
        "contributor": "Dang Le",
        "new_color": "#D2EFFB",
        "color": "rgba(0, 179, 249, 0.16)"
      }
]